milvusmodel_py-0.1.2.dist-info/licenses/LICENSE
pymilvusmodel/__init__.py
pymilvusmodel/index.py
pymilvusmodel/model.py
milvusmodel_py-0.1.2.dist-info/METADATA
milvusmodel_py-0.1.2.dist-info/WHEEL
milvusmodel_py-0.1.2.dist-info/top_level.txt
milvusmodel_py-0.1.2.dist-info/RECORD
