Metadata-Version: 2.4
Name: milvusmodel.py
Version: 0.1.2
Summary: SQLModel-like library for Milvus
Author-email: Brian Ferri <me@brianferri.dev>
Project-URL: Homepage, https://github.com/brianferri/PyMilvusModel
Project-URL: Issues, https://github.com/brianferri/PyMilvusModel/issues
Classifier: Programming Language :: Python :: 3.11
Classifier: Operating System :: OS Independent
Classifier: Topic :: Database
Classifier: Topic :: Database :: Database Engines/Servers
Classifier: Typing :: Typed
Requires-Python: >=3.11
License-File: LICENSE
Requires-Dist: pydantic>=2.9.2
Requires-Dist: pydantic-core>=2.23.4
Requires-Dist: pymilvus>=2.5.4
Dynamic: license-file
